Workbook

Sheet Dashboard
A1: Portfolio Dashboard
A2: =Settings!B4&" | Benchmark: "&Settings!$B$7&" | Since "&TEXT(Settings!$B$5,"yyyy-mm-dd")
A4: Performance | D4: Sector allocation | E4: Weight | F4: Value
A5: Portfolio value | B5: =Holdings!H17 | D5: =SORT(UNIQUE(FILTER(Holdings!C5:C14,Holdings!A5:A14<>""))) | E5: =ARRAYFORMULA(IF(D5:D14="",,F5:F14/Holdings!H17)) | F5: =ARRAYFORMULA(IF(D5:D14="",,SUMIF(Holdings!C5:C14,D5:D14,Holdings!H5:H14)))
A6: Starting capital | B6: =Settings!$B$6
A7: Total return | B7: =Holdings!H17/Settings!$B$6-1
A8: Benchmark return | B8: =IFERROR(GOOGLEFINANCE(Settings!$B$7)/Prices!B4-1,"")
A9: Excess return vs benchmark | B9: =B7-B8
A10: Trading days tracked | B10: =COUNT(History!A4:A1003)
A11: Risk-adjusted (daily returns, annualized)
A12: Beta vs benchmark | B12: =IFERROR(SLOPE(History!R5:R1003,History!S5:S1003),"")
A13: Jensen's alpha (annual) | B13: =IFERROR((AVERAGE(History!R5:R1003)-Settings!$B$8/252-B12*(AVERAGE(History!S5:S1003)-Settings!$B$8/252))*252,"")
A14: Correlation with benchmark | B14: =IFERROR(CORREL(History!R5:R1003,History!S5:S1003),"")
A15: Portfolio volatility | B15: =IFERROR(STDEV(History!R5:R1003)*SQRT(252),"") | D15: Cash | E15: =Holdings!I16 | F15: =Holdings!H16
A16: Benchmark volatility | B16: =IFERROR(STDEV(History!S5:S1003)*SQRT(252),"")
A17: Sharpe ratio | B17: =IFERROR((AVERAGE(History!R5:R1003)*252-Settings!$B$8)/B15,"")
A18: Drawdown
A19: Max drawdown (portfolio) | B19: =MIN(History!U4:U1003)
A20: Max drawdown (benchmark) | B20: =MIN(History!W4:W1003)
A21: Current drawdown | B21: =IFERROR(INDEX(History!U4:U1003,B10),"")

Sheet Holdings
A1: Holdings
A2: Enter a ticker and sector in each slot (yellow). Shares and cost come from the Trades tab; prices are live.
A4: Ticker | B4: Name | C4: Sector | D4: Shares | E4: Avg cost | F4: Live price | G4: Day chg | H4: Market value | I4: Weight | J4: Cost basis | K4: Unrealized P/L | L4: Return | M4: Beta
A5: AAPL | B5: =IF(A5="","",IFERROR(GOOGLEFINANCE(A5,"name"),"")) | C5: Information Technology | D5: =IF(A5="","",SUMIFS(Trades!$G$5:$G$204,Trades!$B$5:$B$204,A5)) | E5: =IF(A5="","",IFERROR(SUMPRODUCT((Trades!$B$5:$B$204=A5)*(Trades!$C$5:$C$204="BUY"),Trades!$D$5:$D$204,Trades!$E$5:$E$204)/SUMIFS(Trades!$D$5:$D$204,Trades!$B$5:$B$204,A5,Trades!$C$5:$C$204,"BUY"),"")) | F5: =IF(A5="","",IFERROR(GOOGLEFINANCE(A5),"")) | G5: =IF(A5="","",IFERROR(GOOGLEFINANCE(A5,"changepct")/100,"")) | H5: =IF(A5="","",IFERROR(D5*F5,0)) | I5: =IF(A5="","",IFERROR(H5/$H$17,"")) | J5: =IF(A5="","",IFERROR(D5*E5,0)) | K5: =IF(A5="","",H5-J5) | L5: =IF(A5="","",IFERROR(K5/J5,"")) | M5: =IF(A5="","",IFERROR(GOOGLEFINANCE(A5,"beta"),""))
A6: MSFT | B6: =IF(A6="","",IFERROR(GOOGLEFINANCE(A6,"name"),"")) | C6: Information Technology | D6: =IF(A6="","",SUMIFS(Trades!$G$5:$G$204,Trades!$B$5:$B$204,A6)) | E6: =IF(A6="","",IFERROR(SUMPRODUCT((Trades!$B$5:$B$204=A6)*(Trades!$C$5:$C$204="BUY"),Trades!$D$5:$D$204,Trades!$E$5:$E$204)/SUMIFS(Trades!$D$5:$D$204,Trades!$B$5:$B$204,A6,Trades!$C$5:$C$204,"BUY"),"")) | F6: =IF(A6="","",IFERROR(GOOGLEFINANCE(A6),"")) | G6: =IF(A6="","",IFERROR(GOOGLEFINANCE(A6,"changepct")/100,"")) | H6: =IF(A6="","",IFERROR(D6*F6,0)) | I6: =IF(A6="","",IFERROR(H6/$H$17,"")) | J6: =IF(A6="","",IFERROR(D6*E6,0)) | K6: =IF(A6="","",H6-J6) | L6: =IF(A6="","",IFERROR(K6/J6,"")) | M6: =IF(A6="","",IFERROR(GOOGLEFINANCE(A6,"beta"),""))
A7: JPM | B7: =IF(A7="","",IFERROR(GOOGLEFINANCE(A7,"name"),"")) | C7: Financials | D7: =IF(A7="","",SUMIFS(Trades!$G$5:$G$204,Trades!$B$5:$B$204,A7)) | E7: =IF(A7="","",IFERROR(SUMPRODUCT((Trades!$B$5:$B$204=A7)*(Trades!$C$5:$C$204="BUY"),Trades!$D$5:$D$204,Trades!$E$5:$E$204)/SUMIFS(Trades!$D$5:$D$204,Trades!$B$5:$B$204,A7,Trades!$C$5:$C$204,"BUY"),"")) | F7: =IF(A7="","",IFERROR(GOOGLEFINANCE(A7),"")) | G7: =IF(A7="","",IFERROR(GOOGLEFINANCE(A7,"changepct")/100,"")) | H7: =IF(A7="","",IFERROR(D7*F7,0)) | I7: =IF(A7="","",IFERROR(H7/$H$17,"")) | J7: =IF(A7="","",IFERROR(D7*E7,0)) | K7: =IF(A7="","",H7-J7) | L7: =IF(A7="","",IFERROR(K7/J7,"")) | M7: =IF(A7="","",IFERROR(GOOGLEFINANCE(A7,"beta"),""))
A8: XOM | B8: =IF(A8="","",IFERROR(GOOGLEFINANCE(A8,"name"),"")) | C8: Energy | D8: =IF(A8="","",SUMIFS(Trades!$G$5:$G$204,Trades!$B$5:$B$204,A8)) | E8: =IF(A8="","",IFERROR(SUMPRODUCT((Trades!$B$5:$B$204=A8)*(Trades!$C$5:$C$204="BUY"),Trades!$D$5:$D$204,Trades!$E$5:$E$204)/SUMIFS(Trades!$D$5:$D$204,Trades!$B$5:$B$204,A8,Trades!$C$5:$C$204,"BUY"),"")) | F8: =IF(A8="","",IFERROR(GOOGLEFINANCE(A8),"")) | G8: =IF(A8="","",IFERROR(GOOGLEFINANCE(A8,"changepct")/100,"")) | H8: =IF(A8="","",IFERROR(D8*F8,0)) | I8: =IF(A8="","",IFERROR(H8/$H$17,"")) | J8: =IF(A8="","",IFERROR(D8*E8,0)) | K8: =IF(A8="","",H8-J8) | L8: =IF(A8="","",IFERROR(K8/J8,"")) | M8: =IF(A8="","",IFERROR(GOOGLEFINANCE(A8,"beta"),""))
A9: PG | B9: =IF(A9="","",IFERROR(GOOGLEFINANCE(A9,"name"),"")) | C9: Consumer Staples | D9: =IF(A9="","",SUMIFS(Trades!$G$5:$G$204,Trades!$B$5:$B$204,A9)) | E9: =IF(A9="","",IFERROR(SUMPRODUCT((Trades!$B$5:$B$204=A9)*(Trades!$C$5:$C$204="BUY"),Trades!$D$5:$D$204,Trades!$E$5:$E$204)/SUMIFS(Trades!$D$5:$D$204,Trades!$B$5:$B$204,A9,Trades!$C$5:$C$204,"BUY"),"")) | F9: =IF(A9="","",IFERROR(GOOGLEFINANCE(A9),"")) | G9: =IF(A9="","",IFERROR(GOOGLEFINANCE(A9,"changepct")/100,"")) | H9: =IF(A9="","",IFERROR(D9*F9,0)) | I9: =IF(A9="","",IFERROR(H9/$H$17,"")) | J9: =IF(A9="","",IFERROR(D9*E9,0)) | K9: =IF(A9="","",H9-J9) | L9: =IF(A9="","",IFERROR(K9/J9,"")) | M9: =IF(A9="","",IFERROR(GOOGLEFINANCE(A9,"beta"),""))
A10: UNH | B10: =IF(A10="","",IFERROR(GOOGLEFINANCE(A10,"name"),"")) | C10: Health Care | D10: =IF(A10="","",SUMIFS(Trades!$G$5:$G$204,Trades!$B$5:$B$204,A10)) | E10: =IF(A10="","",IFERROR(SUMPRODUCT((Trades!$B$5:$B$204=A10)*(Trades!$C$5:$C$204="BUY"),Trades!$D$5:$D$204,Trades!$E$5:$E$204)/SUMIFS(Trades!$D$5:$D$204,Trades!$B$5:$B$204,A10,Trades!$C$5:$C$204,"BUY"),"")) | F10: =IF(A10="","",IFERROR(GOOGLEFINANCE(A10),"")) | G10: =IF(A10="","",IFERROR(GOOGLEFINANCE(A10,"changepct")/100,"")) | H10: =IF(A10="","",IFERROR(D10*F10,0)) | I10: =IF(A10="","",IFERROR(H10/$H$17,"")) | J10: =IF(A10="","",IFERROR(D10*E10,0)) | K10: =IF(A10="","",H10-J10) | L10: =IF(A10="","",IFERROR(K10/J10,"")) | M10: =IF(A10="","",IFERROR(GOOGLEFINANCE(A10,"beta"),""))
A11: CAT | B11: =IF(A11="","",IFERROR(GOOGLEFINANCE(A11,"name"),"")) | C11: Industrials | D11: =IF(A11="","",SUMIFS(Trades!$G$5:$G$204,Trades!$B$5:$B$204,A11)) | E11: =IF(A11="","",IFERROR(SUMPRODUCT((Trades!$B$5:$B$204=A11)*(Trades!$C$5:$C$204="BUY"),Trades!$D$5:$D$204,Trades!$E$5:$E$204)/SUMIFS(Trades!$D$5:$D$204,Trades!$B$5:$B$204,A11,Trades!$C$5:$C$204,"BUY"),"")) | F11: =IF(A11="","",IFERROR(GOOGLEFINANCE(A11),"")) | G11: =IF(A11="","",IFERROR(GOOGLEFINANCE(A11,"changepct")/100,"")) | H11: =IF(A11="","",IFERROR(D11*F11,0)) | I11: =IF(A11="","",IFERROR(H11/$H$17,"")) | J11: =IF(A11="","",IFERROR(D11*E11,0)) | K11: =IF(A11="","",H11-J11) | L11: =IF(A11="","",IFERROR(K11/J11,"")) | M11: =IF(A11="","",IFERROR(GOOGLEFINANCE(A11,"beta"),""))
A12: NEE | B12: =IF(A12="","",IFERROR(GOOGLEFINANCE(A12,"name"),"")) | C12: Utilities | D12: =IF(A12="","",SUMIFS(Trades!$G$5:$G$204,Trades!$B$5:$B$204,A12)) | E12: =IF(A12="","",IFERROR(SUMPRODUCT((Trades!$B$5:$B$204=A12)*(Trades!$C$5:$C$204="BUY"),Trades!$D$5:$D$204,Trades!$E$5:$E$204)/SUMIFS(Trades!$D$5:$D$204,Trades!$B$5:$B$204,A12,Trades!$C$5:$C$204,"BUY"),"")) | F12: =IF(A12="","",IFERROR(GOOGLEFINANCE(A12),"")) | G12: =IF(A12="","",IFERROR(GOOGLEFINANCE(A12,"changepct")/100,"")) | H12: =IF(A12="","",IFERROR(D12*F12,0)) | I12: =IF(A12="","",IFERROR(H12/$H$17,"")) | J12: =IF(A12="","",IFERROR(D12*E12,0)) | K12: =IF(A12="","",H12-J12) | L12: =IF(A12="","",IFERROR(K12/J12,"")) | M12: =IF(A12="","",IFERROR(GOOGLEFINANCE(A12,"beta"),""))
B13: =IF(A13="","",IFERROR(GOOGLEFINANCE(A13,"name"),"")) | D13: =IF(A13="","",SUMIFS(Trades!$G$5:$G$204,Trades!$B$5:$B$204,A13)) | E13: =IF(A13="","",IFERROR(SUMPRODUCT((Trades!$B$5:$B$204=A13)*(Trades!$C$5:$C$204="BUY"),Trades!$D$5:$D$204,Trades!$E$5:$E$204)/SUMIFS(Trades!$D$5:$D$204,Trades!$B$5:$B$204,A13,Trades!$C$5:$C$204,"BUY"),"")) | F13: =IF(A13="","",IFERROR(GOOGLEFINANCE(A13),"")) | G13: =IF(A13="","",IFERROR(GOOGLEFINANCE(A13,"changepct")/100,"")) | H13: =IF(A13="","",IFERROR(D13*F13,0)) | I13: =IF(A13="","",IFERROR(H13/$H$17,"")) | J13: =IF(A13="","",IFERROR(D13*E13,0)) | K13: =IF(A13="","",H13-J13) | L13: =IF(A13="","",IFERROR(K13/J13,"")) | M13: =IF(A13="","",IFERROR(GOOGLEFINANCE(A13,"beta"),""))
B14: =IF(A14="","",IFERROR(GOOGLEFINANCE(A14,"name"),"")) | D14: =IF(A14="","",SUMIFS(Trades!$G$5:$G$204,Trades!$B$5:$B$204,A14)) | E14: =IF(A14="","",IFERROR(SUMPRODUCT((Trades!$B$5:$B$204=A14)*(Trades!$C$5:$C$204="BUY"),Trades!$D$5:$D$204,Trades!$E$5:$E$204)/SUMIFS(Trades!$D$5:$D$204,Trades!$B$5:$B$204,A14,Trades!$C$5:$C$204,"BUY"),"")) | F14: =IF(A14="","",IFERROR(GOOGLEFINANCE(A14),"")) | G14: =IF(A14="","",IFERROR(GOOGLEFINANCE(A14,"changepct")/100,"")) | H14: =IF(A14="","",IFERROR(D14*F14,0)) | I14: =IF(A14="","",IFERROR(H14/$H$17,"")) | J14: =IF(A14="","",IFERROR(D14*E14,0)) | K14: =IF(A14="","",H14-J14) | L14: =IF(A14="","",IFERROR(K14/J14,"")) | M14: =IF(A14="","",IFERROR(GOOGLEFINANCE(A14,"beta"),""))
A15: Total equities | H15: =SUM(H5:H14) | I15: =IFERROR(H15/H17,0) | J15: =SUM(J5:J14) | K15: =H15-J15 | L15: =IFERROR(K15/J15,0)
A16: Cash | H16: =Settings!$B$6+SUM(Trades!$H$5:$H$204) | I16: =IFERROR(H16/H17,0)
A17: Total portfolio | H17: =H15+H16 | I17: =H15/H17+I16

Sheet Trades
A1: Trade Log & Investment Thesis
A2: Log every buy/sell with the reasoning behind it. Price defaults to that day's close via GOOGLEFINANCE; overwrite it with your actual fill if you have one.
A4: Date | B4: Ticker | C4: Action | D4: Shares | E4: Price | F4: Fees | G4: Signed shares | H4: Cash flow | I4: Thesis | J4: Catalyst | K4: Key risk | L4: Exit / review trigger
A5: 46024 | B5: AAPL | C5: BUY | D5: 40 | E5: =IFERROR(INDEX(GOOGLEFINANCE(B5,"close",A5),2,2),"") | F5: 0 | G5: =ARRAYFORMULA(IF(B5:B204="",,IF(C5:C204="SELL",-D5:D204,D5:D204))) | H5: =ARRAYFORMULA(IF(B5:B204="",,-G5:G204*E5:E204-F5:F204)) | I5: Example: cash-generative mega-cap; services mix supports margins | J5: Next earnings / product cycle | K5: Hardware demand slowdown | L5: Sell if services growth stalls two quarters in a row
A6: 46024 | B6: MSFT | C6: BUY | D6: 20 | E6: =IFERROR(INDEX(GOOGLEFINANCE(B6,"close",A6),2,2),"") | F6: 0 | I6: Example: cloud + enterprise software compounder | J6: Cloud growth at earnings | K6: AI capex not earning a return | L6: Trim if weight exceeds 15%
A7: 46024 | B7: JPM | C7: BUY | D7: 32 | E7: =IFERROR(INDEX(GOOGLEFINANCE(B7,"close",A7),2,2),"") | F7: 0 | I7: Example: best-in-class bank, benefits from higher-for-longer rates | J7: Net interest income guidance | K7: Credit losses rise in a slowdown | L7: Review if rate cuts compress NII
A8: 46024 | B8: XOM | C8: BUY | D8: 85 | E8: =IFERROR(INDEX(GOOGLEFINANCE(B8,"close",A8),2,2),"") | F8: 0 | I8: Example: energy exposure as an inflation hedge | J8: Oil price / OPEC decisions | K8: Oil price collapse | L8: Cut if position falls 15% below cost
A9: 46024 | B9: PG | C9: BUY | D9: 65 | E9: =IFERROR(INDEX(GOOGLEFINANCE(B9,"close",A9),2,2),"") | F9: 0 | I9: Example: low-beta defensive ballast | J9: Pricing power in quarterly results | K9: Volume declines from price hikes | L9: Hold as long as it lowers portfolio beta
A10: 46024 | B10: UNH | C10: BUY | D10: 30 | E10: =IFERROR(INDEX(GOOGLEFINANCE(B10,"close",A10),2,2),"") | F10: 0 | I10: Example: healthcare diversification | J10: Medical cost trend updates | K10: Regulatory / reimbursement changes | L10: Exit on a guidance cut
A11: 46024 | B11: CAT | C11: BUY | D11: 18 | E11: =IFERROR(INDEX(GOOGLEFINANCE(B11,"close",A11),2,2),"") | F11: 0 | I11: Example: cyclical play on infrastructure spending | J11: Order backlog at earnings | K11: Industrial recession | L11: Trim if backlog shrinks
A12: 46024 | B12: NEE | C12: BUY | D12: 130 | E12: =IFERROR(INDEX(GOOGLEFINANCE(B12,"close",A12),2,2),"") | F12: 0 | I12: Example: utilities exposure and rate sensitivity | J12: Rate cuts | K12: Rates stay high | L12: Review if 10y yield rises sharply
A13: 46174 | B13: XOM | C13: SELL | D13: 25 | E13: =IFERROR(INDEX(GOOGLEFINANCE(B13,"close",A13),2,2),"") | F13: 0 | I13: Example: trim to rebalance energy weight

Sheet Settings
A1: Settings
A2: Yellow cells with blue text are inputs. Everything else is calculated.
A4: Portfolio name | B4: Mock Equity Portfolio
A5: Start date (inception) | B5: 46024
A6: Starting cash | B6: 100000
A7: Benchmark ticker | B7: SPY
A8: Risk-free rate (annual) | B8: 0.04
A11: Notes
A12: • Prices come from GOOGLEFINANCE and can be delayed up to 20 minutes.
A13: • Benchmark: SPY tracks the S&P 500. For the S&P/TSX use XIC (TSE:XIC), and keep holdings in the same currency so returns are comparable.
A14: • Returns are price returns; dividends are not included.
A15: • Every ticker you trade must also be listed in a Holdings slot.
A16: • History covers up to 1,000 trading days from the start date.

Sheet History
A1: Daily History
A2: Portfolio value is rebuilt each day from the trade log and closing prices. Don't type here.
A3: Date | B3: Benchmark close | C3: =IF(Holdings!A5="","Slot 1",Holdings!A5&" value") | D3: =IF(Holdings!A6="","Slot 2",Holdings!A6&" value") | E3: =IF(Holdings!A7="","Slot 3",Holdings!A7&" value") | F3: =IF(Holdings!A8="","Slot 4",Holdings!A8&" value") | G3: =IF(Holdings!A9="","Slot 5",Holdings!A9&" value") | H3: =IF(Holdings!A10="","Slot 6",Holdings!A10&" value") | I3: =IF(Holdings!A11="","Slot 7",Holdings!A11&" value") | J3: =IF(Holdings!A12="","Slot 8",Holdings!A12&" value") | K3: =IF(Holdings!A13="","Slot 9",Holdings!A13&" value") | L3: =IF(Holdings!A14="","Slot 10",Holdings!A14&" value") | M3: Equities | N3: Cash | O3: Portfolio value | P3: Portfolio (base 100) | Q3: Benchmark (base 100) | R3: Portfolio daily ret | S3: Benchmark daily ret | T3: Portfolio peak | U3: Portfolio drawdown | V3: Benchmark peak | W3: Benchmark drawdown
A4: =ARRAYFORMULA(IF(Prices!A4:A1003="",,Prices!A4:A1003)) | B4: =ARRAYFORMULA(IF(Prices!A4:A1003="",,Prices!B4:B1003)) | C4: =IF(Holdings!$A$5="",,MAP($A4:$A1003,LAMBDA(d,IF(d="",,SUMIFS(Trades!$G$5:$G$204,Trades!$B$5:$B$204,Holdings!$A$5,Trades!$A$5:$A$204,"<="&d)*IFERROR(XLOOKUP(d,Prices!$C$4:$C$1003,Prices!$D$4:$D$1003,0,-1),0))))) | D4: =IF(Holdings!$A$6="",,MAP($A4:$A1003,LAMBDA(d,IF(d="",,SUMIFS(Trades!$G$5:$G$204,Trades!$B$5:$B$204,Holdings!$A$6,Trades!$A$5:$A$204,"<="&d)*IFERROR(XLOOKUP(d,Prices!$E$4:$E$1003,Prices!$F$4:$F$1003,0,-1),0))))) | E4: =IF(Holdings!$A$7="",,MAP($A4:$A1003,LAMBDA(d,IF(d="",,SUMIFS(Trades!$G$5:$G$204,Trades!$B$5:$B$204,Holdings!$A$7,Trades!$A$5:$A$204,"<="&d)*IFERROR(XLOOKUP(d,Prices!$G$4:$G$1003,Prices!$H$4:$H$1003,0,-1),0))))) | F4: =IF(Holdings!$A$8="",,MAP($A4:$A1003,LAMBDA(d,IF(d="",,SUMIFS(Trades!$G$5:$G$204,Trades!$B$5:$B$204,Holdings!$A$8,Trades!$A$5:$A$204,"<="&d)*IFERROR(XLOOKUP(d,Prices!$I$4:$I$1003,Prices!$J$4:$J$1003,0,-1),0))))) | G4: =IF(Holdings!$A$9="",,MAP($A4:$A1003,LAMBDA(d,IF(d="",,SUMIFS(Trades!$G$5:$G$204,Trades!$B$5:$B$204,Holdings!$A$9,Trades!$A$5:$A$204,"<="&d)*IFERROR(XLOOKUP(d,Prices!$K$4:$K$1003,Prices!$L$4:$L$1003,0,-1),0))))) | H4: =IF(Holdings!$A$10="",,MAP($A4:$A1003,LAMBDA(d,IF(d="",,SUMIFS(Trades!$G$5:$G$204,Trades!$B$5:$B$204,Holdings!$A$10,Trades!$A$5:$A$204,"<="&d)*IFERROR(XLOOKUP(d,Prices!$M$4:$M$1003,Prices!$N$4:$N$1003,0,-1),0))))) | I4: =IF(Holdings!$A$11="",,MAP($A4:$A1003,LAMBDA(d,IF(d="",,SUMIFS(Trades!$G$5:$G$204,Trades!$B$5:$B$204,Holdings!$A$11,Trades!$A$5:$A$204,"<="&d)*IFERROR(XLOOKUP(d,Prices!$O$4:$O$1003,Prices!$P$4:$P$1003,0,-1),0))))) | J4: =IF(Holdings!$A$12="",,MAP($A4:$A1003,LAMBDA(d,IF(d="",,SUMIFS(Trades!$G$5:$G$204,Trades!$B$5:$B$204,Holdings!$A$12,Trades!$A$5:$A$204,"<="&d)*IFERROR(XLOOKUP(d,Prices!$Q$4:$Q$1003,Prices!$R$4:$R$1003,0,-1),0))))) | K4: =IF(Holdings!$A$13="",,MAP($A4:$A1003,LAMBDA(d,IF(d="",,SUMIFS(Trades!$G$5:$G$204,Trades!$B$5:$B$204,Holdings!$A$13,Trades!$A$5:$A$204,"<="&d)*IFERROR(XLOOKUP(d,Prices!$S$4:$S$1003,Prices!$T$4:$T$1003,0,-1),0))))) | L4: =IF(Holdings!$A$14="",,MAP($A4:$A1003,LAMBDA(d,IF(d="",,SUMIFS(Trades!$G$5:$G$204,Trades!$B$5:$B$204,Holdings!$A$14,Trades!$A$5:$A$204,"<="&d)*IFERROR(XLOOKUP(d,Prices!$U$4:$U$1003,Prices!$V$4:$V$1003,0,-1),0))))) | M4: =ARRAYFORMULA(IF(A4:A1003="",,MMULT(IFERROR(C4:L1003*1,0),SEQUENCE(10,1,1,0)))) | N4: =MAP(A4:A1003,LAMBDA(d,IF(d="",,Settings!$B$6+SUMIFS(Trades!$H$5:$H$204,Trades!$A$5:$A$204,"<="&d)))) | O4: =ARRAYFORMULA(IF(A4:A1003="",,M4:M1003+N4:N1003)) | P4: =ARRAYFORMULA(IF(A4:A1003="",,O4:O1003/$O$4*100)) | Q4: =ARRAYFORMULA(IF(A4:A1003="",,B4:B1003/$B$4*100)) | T4: =SCAN(0,O4:O1003,LAMBDA(a,v,IF(v="",a,MAX(a,v)))) | U4: =ARRAYFORMULA(IF(A4:A1003="",,O4:O1003/T4:T1003-1)) | V4: =SCAN(0,B4:B1003,LAMBDA(a,v,IF(v="",a,MAX(a,v)))) | W4: =ARRAYFORMULA(IF(A4:A1003="",,B4:B1003/V4:V1003-1))
R5: =ARRAYFORMULA(IF(A5:A1003="",,O5:O1003/O4:O1002-1)) | S5: =ARRAYFORMULA(IF(A5:A1003="",,B5:B1003/B4:B1002-1))

Sheet Prices
A1: Raw Prices
A2: Daily closes from GOOGLEFINANCE, starting at the Settings start date. Don't type here.
A3: =GOOGLEFINANCE(Settings!$B$7,"close",Settings!$B$5,TODAY(),"DAILY") | C3: =IFERROR(GOOGLEFINANCE(Holdings!$A$5,"close",Settings!$B$5,TODAY(),"DAILY"),"") | E3: =IFERROR(GOOGLEFINANCE(Holdings!$A$6,"close",Settings!$B$5,TODAY(),"DAILY"),"") | G3: =IFERROR(GOOGLEFINANCE(Holdings!$A$7,"close",Settings!$B$5,TODAY(),"DAILY"),"") | I3: =IFERROR(GOOGLEFINANCE(Holdings!$A$8,"close",Settings!$B$5,TODAY(),"DAILY"),"") | K3: =IFERROR(GOOGLEFINANCE(Holdings!$A$9,"close",Settings!$B$5,TODAY(),"DAILY"),"") | M3: =IFERROR(GOOGLEFINANCE(Holdings!$A$10,"close",Settings!$B$5,TODAY(),"DAILY"),"") | O3: =IFERROR(GOOGLEFINANCE(Holdings!$A$11,"close",Settings!$B$5,TODAY(),"DAILY"),"") | Q3: =IFERROR(GOOGLEFINANCE(Holdings!$A$12,"close",Settings!$B$5,TODAY(),"DAILY"),"") | S3: =IFERROR(GOOGLEFINANCE(Holdings!$A$13,"close",Settings!$B$5,TODAY(),"DAILY"),"") | U3: =IFERROR(GOOGLEFINANCE(Holdings!$A$14,"close",Settings!$B$5,TODAY(),"DAILY"),"")
